wsid.py
wsid-1.1.dist-info/METADATA
wsid-1.1.dist-info/WHEEL
wsid-1.1.dist-info/entry_points.txt
wsid-1.1.dist-info/top_level.txt
wsid-1.1.dist-info/RECORD
