Metadata-Version: 2.1
Name: wsid
Version: 1.1
Summary: web show image directory
Home-page: https://github.com/matheuz1210/wsid
Author: matheuz1210
Author-email: matheuz1210@gmail.com
License: GPLv2+
Platform: UNKNOWN
Classifier: License :: OSI Approved :: GNU General Public License v2 or later (GPLv2+)
Classifier: Operating System :: OS Independent
Classifier: Programming Language :: Python :: 3
Classifier: Programming Language :: Python :: 3.7
Classifier: Programming Language :: Python :: 3.8
Classifier: Programming Language :: Python :: 3.9
Classifier: Programming Language :: Python :: 3.10
Requires-Python: >=3.7
Provides-Extra: gui
Requires-Dist: PyQt5 ; extra == 'gui'
